dammy7878carberra/__init__.py
dammy7878carberra/__main__.py
dammy7878carberra/cli.py
dammy7878carberra-0.1.0.dist-info/METADATA
dammy7878carberra-0.1.0.dist-info/WHEEL
dammy7878carberra-0.1.0.dist-info/entry_points.txt
dammy7878carberra-0.1.0.dist-info/top_level.txt
dammy7878carberra-0.1.0.dist-info/RECORD
